jinja2_ansible_filters/__init__.py
jinja2_ansible_filters/ansible_utils.py
jinja2_ansible_filters/core_filters.py
jinja2_ansible_filters/module_utils.py
jinja2_ansible_filters-1.3.2.dist-info/LICENSE
jinja2_ansible_filters-1.3.2.dist-info/METADATA
jinja2_ansible_filters-1.3.2.dist-info/WHEEL
jinja2_ansible_filters-1.3.2.dist-info/top_level.txt
jinja2_ansible_filters-1.3.2.dist-info/RECORD
