Metadata-Version: 2.1
Name: jinja2-ansible-filters
Version: 1.3.2
Summary: A port of Ansible's jinja2 filters without requiring ansible core.
Home-page: https://gitlab.com/dreamer-labs/libraries/jinja2-ansible-filters
Author: Nick Shobe
Author-email: nickshobe@gmail.com
License: GPL3
Provides-Extra: test
License-File: LICENSE
